{
    "username": "betsymp",
    "submission": "#include <bits/stdc++.h>\n#include <ext/pb_ds/assoc_container.hpp>\n\nusing namespace std;\nusing namespace __gnu_pbds;\n\n#pragma region\ntemplate <typename T>\nusing ordered_set = tree<T, null_type, less<T>, rb_tree_tag, tree_order_statistics_node_update>;\n\n#define ll long long\n#define sz(x) (int)(x).size()\n#define mp make_pair\n#define pb push_back\n#define f first\n#define s second\n#define lb lower_bound\n#define ub upper_bound\n#define all(x) x.begin(), x.end()\n#define rall(x) x.rbegin(), x.rend()\n#define ins insert\n\nvoid __print(int x) { cout << x; }\nvoid __print(long x) { cout << x; }\nvoid __print(long long x) { cout << x; }\nvoid __print(unsigned x) { cout << x; }\nvoid __print(unsigned long x) { cout << x; }\nvoid __print(unsigned long long x) { cout << x; }\nvoid __print(float x) { cout << x; }\nvoid __print(double x) { cout << x; }\nvoid __print(long double x) { cout << x; }\nvoid __print(char x) { cout << '\\'' << x << '\\''; }\nvoid __print(const char *x) { cout << '\\\"' << x << '\\\"'; }\nvoid __print(const string &x) { cout << '\\\"' << x << '\\\"'; }\nvoid __print(bool x) { cout << (x ? \"true\" : \"false\"); }\ntemplate <size_t N>\nvoid __print(const bitset<N>& x) { cout << x; };\n\ntemplate <typename T>\nvoid __print(const T &x);\ntemplate <typename T, typename V>\nvoid __print(const pair<T, V> &x);\ntemplate <typename T>\nvoid __print(const T &x);\ntemplate <typename T, typename... V>\nvoid _print(T t, V... v);\n\ntemplate <typename T, typename V>\nvoid __print(const pair<T, V> &x) {\n    cout << '{';\n    __print(x.first);\n    cout << \", \";\n    __print(x.second);\n    cout << '}';\n}\ntemplate <typename T>\nvoid __print(const T &x) {\n    int f = 0;\n    cout << '{';\n    for (auto &i : x) cout << (f++ ? \", \" : \"\"), __print(i);\n    cout << \"}\";\n}\nvoid _print() { cout << \"]\\n\"; }\ntemplate <typename T, typename... V>\nvoid _print(T t, V... v) {\n    __print(t);\n    if (sizeof...(v)) cout << \", \";\n    _print(v...);\n}\n\ntemplate<class T> bool ckmin(T&a, const T& b) { bool B = a > b; a = min(a,b); return B; }\ntemplate<class T> bool ckmax(T&a, const T& b) { bool B = a < b; a = max(a,b); return B; }\n#pragma endregion\n\n#define dbg(x...)                                                            \\\n    cout << \"[\" << __func__ << \":\" << __LINE__ - 9 << \" [\" << #x << \"] = [\"; \\\n    _print(x);                                                               \\\n    cout << endl;\n// #define dbg(x...)\n\nint MOD = 1000000007;\n\nclass Solution {\npublic:\n    long long minimumCost(int m, int n, vector<int>& h, vector<int>& v) {\n        sort(h.begin(), h.end());\n        sort(v.begin(), v.end());\n        \n        long long i = 0, j = 0, p = 1, q = 1;\n        long long r = 0;\n        priority_queue<pair<long long, bool>> pq;\n        \n        for (int x : h) pq.push({x, true});\n        for (int x : v) pq.push({x, false});\n        \n        while (!pq.empty()) {\n            auto [c, i] = pq.top();\n            pq.pop();\n            \n            if (i) {\n                r += c * q;\n                p++;\n            } else {\n                r += c * p;\n                q++;\n            }\n        }\n        \n        return r;\n    }\n};",
    "submit_ts": "1720924602",
    "subm_id": "1320223294"
}