{
    "username": "jatinsingh2012",
    "submission": "class Solution:\n    def maxOperations(self, s: str) -> int:\n        \n        s=list(s)\n        s=s[::-1]\n        count_0=0\n        r=0\n        res=0\n        \n        while r<len(s):\n            if s[r]==\"1\":\n                res+=count_0\n                r+=1\n                continue\n            \n            count_0+=1\n            while r<len(s) and s[r]==\"0\":\n                r+=1\n        \n        return res\n        ",
    "submit_ts": "1721530544",
    "subm_id": "1327936681"
}